civic_scraper/__init__.py
civic_scraper/cli.py
civic_scraper/runner.py
civic_scraper/utils.py
civic_scraper/base/__init__.py
civic_scraper/base/asset.py
civic_scraper/base/cache.py
civic_scraper/base/constants.py
civic_scraper/base/site.py
civic_scraper/platforms/__init__.py
civic_scraper/platforms/civic_clerk/__init__.py
civic_scraper/platforms/civic_clerk/site.py
civic_scraper/platforms/civic_plus/__init__.py
civic_scraper/platforms/civic_plus/parser.py
civic_scraper/platforms/civic_plus/site.py
civic_scraper/platforms/granicus/__init__.py
civic_scraper/platforms/granicus/site.py
civic_scraper/platforms/legistar/__init__.py
civic_scraper/platforms/legistar/site.py
civic_scraper/platforms/primegov/__init__.py
civic_scraper/platforms/primegov/site.py
civic_scraper-0.2.14.dist-info/licenses/LICENSE
tests/__init__.py
tests/civic_clerk_site.py
tests/conftest.py
tests/granicus_site.py
tests/legistar_site.py
tests/primegov_test.py
tests/test_asset.py
tests/test_base_site.py
tests/test_cache.py
tests/test_cache_env_setting.py
tests/test_civic_plus_parser.py
tests/test_civic_plus_site.py
tests/test_cli.py
tests/test_legistar_site.py
tests/test_runner.py
tests/cassettes/test_civic_plus_site/test_scrape_cache_false_default.yaml
tests/cassettes/test_civic_plus_site/test_scrape_cache_true.yaml
tests/cassettes/test_civic_plus_site/test_scrape_current_day_by_default.yaml
tests/cassettes/test_civic_plus_site/test_scrape_defaults.yaml
tests/cassettes/test_civic_plus_site/test_scrape_download_default.yaml
tests/cassettes/test_civic_plus_site/test_scrape_download_filter_both.yaml
tests/cassettes/test_civic_plus_site/test_scrape_download_filter_size.yaml
tests/cassettes/test_civic_plus_site/test_scrape_download_filter_type.yaml
tests/cassettes/test_civic_plus_site/test_scrape_download_true.yaml
tests/cassettes/test_civic_plus_site/test_scrape_no_meetings_for_date.yaml
tests/cassettes/test_civic_plus_site/test_scrape_place_state.yaml
tests/cassettes/test_cli/test_cli_scrape_simple.yaml
civic_scraper-0.2.14.dist-info/METADATA
civic_scraper-0.2.14.dist-info/WHEEL
civic_scraper-0.2.14.dist-info/entry_points.txt
civic_scraper-0.2.14.dist-info/top_level.txt
civic_scraper-0.2.14.dist-info/RECORD
