Metadata-Version: 2.4
Name: civic-scraper
Version: 0.2.14
Summary: Tools for downloading agendas, minutes and other documents produced by local government
Home-page: https://github.com/biglocalnews/civic-scraper
Author: Serdar Tumgoren
Author-email: zstumgoren@gmail.com
License: Apache 2.0 license
Project-URL: Documentation, https://civic-scraper.readthedocs.io
Project-URL: Maintainer, https://github.com/biglocalnews
Project-URL: Source, https://github.com/biglocalnews/civic-scraper
Project-URL: Tracker, https://github.com/biglocalnews/civic-scraper/issues
Classifier: Development Status :: 4 - Beta
Classifier: Environment :: Console
Classifier: Intended Audience :: Developers
Classifier: License :: OSI Approved :: Apache Software License
Classifier: Natural Language :: English
Classifier: Programming Language :: Python :: 3
Classifier: Programming Language :: Python :: 3.9
Classifier: Programming Language :: Python :: 3.10
Classifier: Programming Language :: Python :: 3.11
License-File: LICENSE
Requires-Dist: bs4
Requires-Dist: click
Requires-Dist: click-option-group
Requires-Dist: feedparser
Requires-Dist: requests
Requires-Dist: demjson3
Requires-Dist: scraper-legistar
Dynamic: author
Dynamic: author-email
Dynamic: classifier
Dynamic: description
Dynamic: description-content-type
Dynamic: home-page
Dynamic: license
Dynamic: license-file
Dynamic: project-url
Dynamic: requires-dist
Dynamic: summary
